prettysleeper/__init__.py
prettysleeper/__main__.py
prettysleeper/console.py
prettysleeper-1.1.0.dist-info/METADATA
prettysleeper-1.1.0.dist-info/WHEEL
prettysleeper-1.1.0.dist-info/entry_points.txt
prettysleeper-1.1.0.dist-info/top_level.txt
prettysleeper-1.1.0.dist-info/RECORD
