Metadata-Version: 2.1
Name: prettysleeper
Version: 1.1.0
Summary: psleep; A sleep function with Emoji's. It shows a countdown, progress clock (switching emoji's), and my favorite, the Wizard.
Home-page: https://github.com/NamasteJasutin/wizprint
Author: NamasteJasutin
Author-email: justin.duijn@outlook.com
License: MIT
Platform: UNKNOWN
Classifier: License :: OSI Approved :: MIT License
Classifier: Programming Language :: Python :: 3
Classifier: Programming Language :: Python :: 3.7
Classifier: Operating System :: OS Independent
